sidtools/__init__.py
sidtools/cli - Copy.py
sidtools/cli.py
sidtools/cli_og.py
sidtools/cli_v2.py
sidtools/cli_v3.py
sidtools/s_gpumd.py
sidtools/s_gpumd_v1.py
sidtools/s_gpumd_v2.py
sidtools/s_make.py
sidtools/s_make_old.py
sidtools/s_run.py
sidtools/s_store.py
sidtools/s_store_og.py
sidtools/s_store_v2.py
sidtools-0.2.11.dist-info/METADATA
sidtools-0.2.11.dist-info/WHEEL
sidtools-0.2.11.dist-info/entry_points.txt
sidtools-0.2.11.dist-info/top_level.txt
sidtools-0.2.11.dist-info/RECORD
