Metadata-Version: 2.4
Name: sidtools
Version: 0.2.11
Summary: A package for sidtools utilities
Author: Siddharth Sonti
Author-email: sonti.siddharth1907@gmail.com
Classifier: Programming Language :: Python :: 3
Classifier: License :: OSI Approved :: MIT License
Requires-Python: >=3.6
Dynamic: author
Dynamic: author-email
Dynamic: classifier
Dynamic: requires-python
Dynamic: summary
